bcamp_dl/__init__.py
bcamp_dl/_version.py
bcamp_dl/bcamp_dl.py
bcamp_dl/cli.py
bcamp_dl/py.typed
bcamp_dl-1.0.5.dist-info/LICENSE
bcamp_dl-1.0.5.dist-info/METADATA
bcamp_dl-1.0.5.dist-info/WHEEL
bcamp_dl-1.0.5.dist-info/entry_points.txt
bcamp_dl-1.0.5.dist-info/top_level.txt
bcamp_dl-1.0.5.dist-info/RECORD
