Metadata-Version: 2.1
Name: bcamp-dl
Version: 1.0.5
Summary: Download your collection from Bandcamp.
Author-email: ReK42 <ReK42@users.noreply.github.com>
Maintainer-email: ReK42 <ReK42@users.noreply.github.com>
License: MIT License
Project-URL: Repository, https://github.com/ReK42/bcamp-dl
Project-URL: Issues, https://github.com/ReK42/bcamp-dl/issues
Keywords: bandcamp,music
Classifier: Development Status :: 4 - Beta
Classifier: Environment :: Console
Classifier: Intended Audience :: End Users/Desktop
Classifier: License :: OSI Approved :: MIT License
Classifier: Natural Language :: English
Classifier: Operating System :: OS Independent
Classifier: Programming Language :: Python
Classifier: Programming Language :: Python :: 3
Classifier: Programming Language :: Python :: 3 :: Only
Classifier: Programming Language :: Python :: 3.9
Classifier: Programming Language :: Python :: 3.10
Classifier: Programming Language :: Python :: 3.11
Classifier: Programming Language :: Python :: 3.12
Classifier: Topic :: Multimedia :: Sound/Audio
Classifier: Topic :: System :: Archiving
Classifier: Topic :: Utilities
Classifier: Typing :: Typed
Requires-Python: >=3.9
License-File: LICENSE
Requires-Dist: browser-cookie3 ==0.19.1
Requires-Dist: bs4 ==0.0.2
Requires-Dist: requests ==2.32.3
Requires-Dist: rich ==13.7.1
Provides-Extra: build
Requires-Dist: setuptools ==72.1.0 ; extra == 'build'
Requires-Dist: setuptools-scm ==8.1.0 ; extra == 'build'
Requires-Dist: build ==1.2.1 ; extra == 'build'
Requires-Dist: twine ==5.1.1 ; extra == 'build'
Provides-Extra: test
Requires-Dist: mypy ==1.11.1 ; extra == 'test'
Requires-Dist: ruff ==0.5.5 ; extra == 'test'
Requires-Dist: black ==24.4.2 ; extra == 'test'
Requires-Dist: types-beautifulsoup4 ; extra == 'test'
Requires-Dist: types-requests ; extra == 'test'
